pysecrets/__init__.py
pysecrets/main.py
pysecrets-0.0.3.dist-info/METADATA
pysecrets-0.0.3.dist-info/WHEEL
pysecrets-0.0.3.dist-info/licenses/LICENSE
pysecrets-0.0.3.dist-info/RECORD
