Metadata-Version: 2.1
Name: pysecrets
Version: 0.0.3
Summary: The lightest weight package for loading secrets into a project.
Project-URL: Homepage, https://github.com/spencerwjensen96/pysecrets
Project-URL: Issues, https://github.com/spencerwjensen96/pysecrets/issues
Author-email: Spencer Jensen <spencerwjensen96@gmail.com>
License-File: LICENSE
Classifier: License :: OSI Approved :: MIT License
Classifier: Operating System :: OS Independent
Classifier: Programming Language :: Python :: 3
Requires-Python: >=3.8
